pandasbt/__init__.py
pandasbt/build_timeframe.py
pandasbt/calc_signal.py
pandasbt/calc_stats.py
pandasbt/equity_curve.py
pandasbt/statistics.py
pandasbt/zscore.py
pandasbt-0.2.0.dist-info/LICENSE
pandasbt-0.2.0.dist-info/METADATA
pandasbt-0.2.0.dist-info/WHEEL
pandasbt-0.2.0.dist-info/top_level.txt
pandasbt-0.2.0.dist-info/RECORD
