Metadata-Version: 2.1
Name: pandasbt
Version: 0.2.0
Summary: Simple framework to test your strategies ideias with pandas
Home-page: https://github.com/Janderson/pandasbt
Author: Janderson FFerreira
Author-email: ffjanderson@gmail.com
License: UNKNOWN
Platform: UNKNOWN
Classifier: Programming Language :: Python :: 3
Requires-Python: >=3.6
